callbacks/__init__.py
callbacks/callbacks.py
callbacks-0.3.0.dist-info/AUTHORS
callbacks-0.3.0.dist-info/METADATA
callbacks-0.3.0.dist-info/WHEEL
callbacks-0.3.0.dist-info/pbr.json
callbacks-0.3.0.dist-info/top_level.txt
callbacks-0.3.0.dist-info/RECORD
