Metadata-Version: 2.1
Name: callbacks
Version: 0.3.0
Summary: Simple callbacks using decorators
Home-page: https://github.com/14rcole/callbacks
Author: Ryan Cole
Author-email: rcyoalne@gmail.com
License: LICENSE.txt
Platform: UNKNOWN
